aiologstash2/__init__.py
aiologstash2/base_handler.py
aiologstash2/log.py
aiologstash2/py.typed
aiologstash2/tcp_handler.py
aiologstash2-2.0.1.dist-info/LICENSE
aiologstash2-2.0.1.dist-info/WHEEL
aiologstash2-2.0.1.dist-info/METADATA
aiologstash2-2.0.1.dist-info/RECORD
