Metadata-Version: 2.1
Name: aiologstash2
Version: 2.0.1
Summary: 
Home-page: https://github.com/aviramha/aiologstash2
License: MIT
Author: Aviram Hassan
Author-email: aviramyhassan@gmail.com
Requires-Python: >=3.7,<4.0
Classifier: Development Status :: 4 - Beta
Classifier: Framework :: AsyncIO
Classifier: Intended Audience :: Developers
Classifier: License :: OSI Approved :: MIT License
Classifier: Programming Language :: Python :: 3
Classifier: Programming Language :: Python :: 3.10
Classifier: Programming Language :: Python :: 3.7
Classifier: Programming Language :: Python :: 3.8
Classifier: Programming Language :: Python :: 3.9
Classifier: Topic :: Software Development :: Libraries :: Python Modules
Requires-Dist: async-timeout (>=4.0.2,<5.0.0)
Requires-Dist: python-logstash (>=0.4.6,<0.5.0)
Project-URL: Repository, https://github.com/aviramha/aiologstash2
